aadhaar/__init__.py
aadhaar/detection.py
aadhaar_detection-0.7.dist-info/METADATA
aadhaar_detection-0.7.dist-info/WHEEL
aadhaar_detection-0.7.dist-info/top_level.txt
aadhaar_detection-0.7.dist-info/RECORD
