Metadata-Version: 2.1
Name: aadhaar-detection
Version: 0.7
Summary: Aadhaar card detection library
Home-page: https://github.com/GirinathRG/aadhaarlib/tree/main
Author: Girinath
Author-email: girinathr@simplfin.tech
Classifier: Development Status :: 3 - Alpha
Classifier: Intended Audience :: Developers
Classifier: License :: OSI Approved :: MIT License
Classifier: Programming Language :: Python :: 3
Classifier: Programming Language :: Python :: 3.6
Classifier: Programming Language :: Python :: 3.7
Classifier: Programming Language :: Python :: 3.8
Requires-Dist: numpy
Requires-Dist: opencv-python
Requires-Dist: tensorflow >=2.7
